gadcodegenerator/__init__.py
gadcodegenerator/cli.py
gadcodegenerator/const/__init__.py
gadcodegenerator/const/extenstions.py
gadcodegenerator/const/files.py
gadcodegenerator/const/python.py
gadcodegenerator/const/regexp.py
gadcodegenerator/const/symbols.py
gadcodegenerator/const/syntax.py
gadcodegenerator/os/__init__.py
gadcodegenerator/os/files.py
gadcodegenerator/os/folders.py
gadcodegenerator/os/http.py
gadcodegenerator/parsers/__init__.py
gadcodegenerator/parsers/config.py
gadcodegenerator/utils/__init__.py
gadcodegenerator/utils/paths.py
gadcodegenerator/utils/prints.py
gadcodegenerator/utils/sorting.py
gadcodegenerator/utils/toml.py
tests/__init__.py
tests/test_init.py
gadcodegenerator-0.0.1.dist-info/LICENSE
gadcodegenerator-0.0.1.dist-info/METADATA
gadcodegenerator-0.0.1.dist-info/WHEEL
gadcodegenerator-0.0.1.dist-info/entry_points.txt
gadcodegenerator-0.0.1.dist-info/top_level.txt
gadcodegenerator-0.0.1.dist-info/RECORD
